krylovevsolver/__init__.py
krylovevsolver/dff.py
krylovevsolver/krylov_solver.py
krylovevsolver/wave_equation.py
krylovevsolver/demos/__init__.py
krylovevsolver/demos/demo_solver.py
krylovevsolver-1.0.1.dist-info/LICENSE.txt
krylovevsolver-1.0.1.dist-info/METADATA
krylovevsolver-1.0.1.dist-info/WHEEL
krylovevsolver-1.0.1.dist-info/top_level.txt
krylovevsolver-1.0.1.dist-info/RECORD
