Metadata-Version: 2.1
Name: krylovevsolver
Version: 1.0.1
Summary: A Krylov eigenvalue solver for linear partial differential operators.
Author: Trojanowski M.
License: MIT License
Project-URL: Homepage, https://github.com/Michozord/Kylov_ev_solver
Project-URL: Documentation, https://kylov-ev-solver.readthedocs.io
Keywords: FEM,PDE,Krylov
Classifier: Development Status :: 3 - Alpha
Classifier: License :: OSI Approved :: MIT License
Classifier: Topic :: Scientific/Engineering :: Mathematics
Requires-Python: >=3.12
License-File: LICENSE.txt
Requires-Dist: ngsolve ==6.2.2403
Requires-Dist: netgen
Requires-Dist: scipy
Requires-Dist: numpy
Requires-Dist: matplotlib
